apps/domain/src/main/core/infrastructure/__init__.py
apps/domain/src/main/core/infrastructure/cli.py
apps/domain/src/main/core/infrastructure/tf.py
apps/domain/src/main/core/infrastructure/utils.py
apps/domain/src/main/core/infrastructure/providers/__init__.py
apps/domain/src/main/core/infrastructure/providers/provider.py
apps/domain/src/main/core/infrastructure/providers/aws/__init__.py
apps/domain/src/main/core/infrastructure/providers/aws/aws.py
apps/domain/src/main/core/infrastructure/providers/aws/serverfull.py
apps/domain/src/main/core/infrastructure/providers/aws/serverless.py
apps/domain/src/main/core/infrastructure/providers/aws/utils.py
apps/domain/src/main/core/infrastructure/providers/azure/__init__.py
apps/domain/src/main/core/infrastructure/providers/azure/azure.py
apps/domain/src/main/core/infrastructure/providers/azure/azure_ts.py
apps/domain/src/main/core/infrastructure/providers/azure/utils.py
apps/domain/src/main/core/infrastructure/providers/gcp/__init__.py
apps/domain/src/main/core/infrastructure/providers/gcp/gcp.py
apps/domain/src/main/core/infrastructure/providers/gcp/utils.py
pygrid_cli-0.5.0.dist-info/LICENSE
pygrid_cli-0.5.0.dist-info/METADATA
pygrid_cli-0.5.0.dist-info/WHEEL
pygrid_cli-0.5.0.dist-info/entry_points.txt
pygrid_cli-0.5.0.dist-info/top_level.txt
pygrid_cli-0.5.0.dist-info/RECORD
