Metadata-Version: 2.1
Name: pygrid-cli
Version: 0.5.0
Summary: OpenMined PyGrid CLI for Infrastructure and cloud deployment
Home-page: https://github.com/OpenMined/PyGrid
License: UNKNOWN
Platform: UNKNOWN
Requires-Dist: click
Requires-Dist: PyInquirer
Requires-Dist: terrascript
Requires-Dist: boto3
